oilpriceapi/__init__.py
oilpriceapi/async_client.py
oilpriceapi/client.py
oilpriceapi/exceptions.py
oilpriceapi/models.py
oilpriceapi/py.typed
oilpriceapi/retry.py
oilpriceapi/visualization.py
oilpriceapi/resources/__init__.py
oilpriceapi/resources/historical.py
oilpriceapi/resources/prices.py
oilpriceapi-1.0.1.dist-info/licenses/LICENSE
oilpriceapi-1.0.1.dist-info/METADATA
oilpriceapi-1.0.1.dist-info/WHEEL
oilpriceapi-1.0.1.dist-info/entry_points.txt
oilpriceapi-1.0.1.dist-info/top_level.txt
oilpriceapi-1.0.1.dist-info/RECORD
