Metadata-Version: 2.4
Name: oilpriceapi
Version: 1.0.1
Summary: Official Python SDK for OilPriceAPI - Real-time and historical oil prices
Author-email: OilPriceAPI <support@oilpriceapi.com>
Maintainer-email: OilPriceAPI Team <support@oilpriceapi.com>
License: MIT License
Project-URL: Homepage, https://oilpriceapi.com
Project-URL: Documentation, https://docs.oilpriceapi.com/sdk/python
Project-URL: Repository, https://github.com/oilpriceapi/python-sdk
Project-URL: Issues, https://github.com/oilpriceapi/python-sdk/issues
Project-URL: Changelog, https://github.com/oilpriceapi/python-sdk/blob/main/CHANGELOG.md
Keywords: oil,prices,api,commodities,energy,brent,wti,natural gas,trading,finance
Classifier: Development Status :: 5 - Production/Stable
Classifier: Intended Audience :: Developers
Classifier: Intended Audience :: Financial and Insurance Industry
Classifier: Intended Audience :: Science/Research
Classifier: License :: OSI Approved :: MIT License
Classifier: Operating System :: OS Independent
Classifier: Programming Language :: Python
Classifier: Programming Language :: Python :: 3
Classifier: Programming Language :: Python :: 3.8
Classifier: Programming Language :: Python :: 3.9
Classifier: Programming Language :: Python :: 3.10
Classifier: Programming Language :: Python :: 3.11
Classifier: Programming Language :: Python :: 3.12
Classifier: Topic :: Office/Business :: Financial
Classifier: Topic :: Scientific/Engineering :: Information Analysis
Classifier: Topic :: Software Development :: Libraries :: Python Modules
Classifier: Typing :: Typed
Requires-Python: >=3.8
License-File: LICENSE
Requires-Dist: httpx>=0.24.0
Requires-Dist: pydantic>=2.0.0
Requires-Dist: python-dateutil>=2.8.0
Requires-Dist: typing-extensions>=4.5.0; python_version < "3.10"
Provides-Extra: pandas
Requires-Dist: pandas>=1.5.0; extra == "pandas"
Requires-Dist: numpy>=1.20.0; extra == "pandas"
Provides-Extra: async
Requires-Dist: aiohttp>=3.8.0; extra == "async"
Provides-Extra: cache
Requires-Dist: redis>=4.5.0; extra == "cache"
Requires-Dist: cachetools>=5.3.0; extra == "cache"
Provides-Extra: cli
Requires-Dist: click>=8.0.0; extra == "cli"
Requires-Dist: rich>=13.0.0; extra == "cli"
Provides-Extra: all
Requires-Dist: oilpriceapi[async,cache,cli,pandas]; extra == "all"
Provides-Extra: dev
Requires-Dist: pytest>=7.0.0; extra == "dev"
Requires-Dist: pytest-cov>=4.0.0; extra == "dev"
Requires-Dist: pytest-asyncio>=0.21.0; extra == "dev"
Requires-Dist: black>=23.0.0; extra == "dev"
Requires-Dist: mypy>=1.0.0; extra == "dev"
Requires-Dist: ruff>=0.0.261; extra == "dev"
Requires-Dist: pre-commit>=3.0.0; extra == "dev"
Dynamic: license-file
